spectrepdf/anonymizer.py
spectrepdf-0.2.1.dist-info/licenses/LICENSE
spectrepdf-0.2.1.dist-info/METADATA
spectrepdf-0.2.1.dist-info/WHEEL
spectrepdf-0.2.1.dist-info/top_level.txt
spectrepdf-0.2.1.dist-info/RECORD
