Metadata-Version: 2.4
Name: SpectrePDF
Version: 0.2.1
Summary: A tool for processing and redacting PDFs based on target words using OCR.
Author-email: Udbhav Ram <udbhavram41@gmail.com>
License-Expression: MIT
Project-URL: Homepage, https://github.com/udiram/SpectrePDF/
Project-URL: Issues, https://github.com/udiram/SpectrePDF/issues
Keywords: pdf,redaction,ocr,security,privacy,text extraction
Classifier: Programming Language :: Python :: 3
Classifier: Operating System :: OS Independent
Requires-Python: >=3.11
License-File: LICENSE
Dynamic: license-file
